LICENSE.md
README.md
pyproject.toml
src/ewoksid12/__init__.py
src/ewoksid12.egg-info/PKG-INFO
src/ewoksid12.egg-info/SOURCES.txt
src/ewoksid12.egg-info/dependency_links.txt
src/ewoksid12.egg-info/entry_points.txt
src/ewoksid12.egg-info/requires.txt
src/ewoksid12.egg-info/top_level.txt
src/ewoksid12/tasks/__init__.py
src/ewoksid12/tasks/hdf5_to_ascii.py
src/ewoksid12/tasks/io.py
src/ewoksid12/tests/__init__.py
src/ewoksid12/tests/test_hdf5_to_ascii.py