Metadata-Version: 2.4
Name: ewoksid12
Version: 2.0.0
Summary: Data processing workflows for ID12
Author-email: ESRF <dau-pydev@esrf.fr>
License: # MIT License
Project-URL: Homepage, https://gitlab.esrf.fr/workflow/ewoksapps/ewoksid12/
Project-URL: Documentation, https://ewoksid12.readthedocs.io/
Project-URL: Repository, https://gitlab.esrf.fr/workflow/ewoksapps/ewoksid12/
Project-URL: Issues, https://gitlab.esrf.fr/workflow/ewoksapps/ewoksid12/issues
Project-URL: Changelog, https://gitlab.esrf.fr/workflow/ewoksapps/ewoksid12/-/blob/main/CHANGELOG.md
Keywords: ewoks
Classifier: Intended Audience :: Science/Research
Classifier: License :: OSI Approved :: MIT License
Classifier: Programming Language :: Python :: 3
Requires-Python: >=3.8
License-File: LICENSE.md
Requires-Dist: ewokscore
Requires-Dist: blissdata
Requires-Dist: numpy
Provides-Extra: test
Requires-Dist: pytest>=7; extra == "test"
Provides-Extra: dev
Requires-Dist: ewoksid12[test]; extra == "dev"
Requires-Dist: black>=25; extra == "dev"
Requires-Dist: flake8>=4; extra == "dev"
Provides-Extra: doc
Requires-Dist: ewoksid12[test]; extra == "doc"
Requires-Dist: sphinx>=4.5; extra == "doc"
Requires-Dist: sphinx-autodoc-typehints>=1.16; extra == "doc"
Requires-Dist: pydata_sphinx_theme; extra == "doc"
Dynamic: license-file
